[{"name":"LA BOURGEONETTE","type":"Amulette","lvl":"Niveau : 32","statistics":[{"% Résistance Terre":{"min":"4","max":"5"}},{"% Résistance Air":{"min":"-5","max":"-undefined"}},{"Force":{"min":"21","max":"30"}},{"Agilité":{"min":"-30","max":"-undefined"}},{"Tacle":{"min":"4","max":"5"}},{"Vitalité":{"min":"31","max":"40"}}]},{"name":"BOTTES PAYSANNES","type":"Bottes","lvl":"Niveau : 32","statistics":[{"Vitalité":{"min":"21","max":"40"}},{"Sagesse":{"min":"11","max":"15"}},{"Chance":{"min":"6","max":"10"}},{"Force":{"min":"6","max":"10"}},{"Dommages":{"min":"1","max":""}}]},{"name":"BOTTES DE PHONG HUSS","type":"Bottes","lvl":"Niveau : 32","statistics":[{"Force":{"min":"16","max":"20"}},{"PO":{"min":"1","max":""}},{}]},{"name":"SAC DU PETIT MOSKITO","type":"Sac à dos","lvl":"Niveau : 32","statistics":[{"Chance":{"min":"11","max":"15"}},{"Retrait PM":{"min":"2","max":"3"}},{"Sagesse":{"min":"11","max":"15"}},{"Prospection":{"min":"3","max":"4"}},{"Vitalité":{"min":"16","max":"25"}}]},{"name":"BOTTES DE RAPINE","type":"Bottes","lvl":"Niveau : 32","statistics":[{"Vitalité":{"min":"6","max":"10"}},{"Soins":{"min":"2","max":"3"}},{}]},{"name":"CEINTURE D'HECTAUPE","type":"Ceinture","lvl":"Niveau : 32","statistics":[{"Agilité":{"min":"16","max":"20"}},{"Dommages":{"min":"1","max":""}},{}]},{"name":"CRYSTAL O'BOUL","type":"Chapeau","lvl":"Niveau : 32","statistics":[{"Vitalité":{"min":"31","max":"40"}},{"Puissance":{"min":"11","max":"15"}},{"Sagesse":{"min":"6","max":"10"}},{"Soins":{"min":"5","max":"8"}}]},{"name":"CAPE RICE","type":"Cape","lvl":"Niveau : 32","statistics":[{"PO":{"min":"2","max":""}},{"Coups Critiques":{"min":"-10","max":"-undefined"}}]},{"name":"CEINTURE BANISATION SAUVAGE","type":"Ceinture","lvl":"Niveau : 32","statistics":[{"Agilité":{"min":"11","max":"20"}},{"Coups Critiques":{"min":"3","max":"5"}},{"Initiative":{"min":"41","max":"65"}}]},{"name":"MITAINES MITÉES DU PAYSAN","type":"Anneau","lvl":"Niveau : 32","statistics":[{"Vitalité":{"min":"11","max":"15"}},{"Invocations":{"min":"1","max":""}},{"% Résistance Air":{"min":"-4","max":"-5"}},{"Force":{"min":"11","max":"15"}}]},{"name":"SAC DU PAYSAN","type":"Sac à dos","lvl":"Niveau : 32","statistics":[{"Chance":{"min":"6","max":"10"}},{"Pods":{"min":"101","max":"200"}},{"Force":{"min":"6","max":"10"}},{"Vitalité":{"min":"21","max":"30"}},{"Fuite":{"min":"2","max":"3"}}]},{"name":"MÉDAILLE HOLY","type":"Amulette","lvl":"Niveau : 31","statistics":[{"Vitalité":{"min":"21","max":"30"}},{"Force":{"min":"21","max":"30"}},{"Tacle":{"min":"2","max":"3"}},{"Dommages Terre":{"min":"2","max":""}},{"Dommages Neutre":{"min":"2","max":""}}]},{"name":"MÉDAILLE LAHILAMA","type":"Amulette","lvl":"Niveau : 31","statistics":[{"Soins":{"min":"4","max":"5"}},{"Vitalité":{"min":"31","max":"40"}},{"Sagesse":{"min":"11","max":"15"}},{"Intelligence":{"min":"16","max":"20"}}]},{"name":"CEINTURE DE RAPINE","type":"Ceinture","lvl":"Niveau : 31","statistics":[{"Intelligence":{"min":"16","max":"20"}},{"Agilité":{"min":"16","max":"20"}},{"Coups Critiques":{"min":"2","max":"3"}},{}]},{"name":"CEINTURE DE PUISSANCE","type":"Ceinture","lvl":"Niveau : 31","statistics":[{"Chance":{"min":"31","max":"40"}},{"Coups Critiques":{"min":"2","max":""}},{"Agilité":{"min":"-30","max":"-undefined"}},{"Dommages Eau":{"min":"2","max":""}},{"Vitalité":{"min":"31","max":"40"}}]},{"name":"ALLIANCE DU CHAMP CHAMP","type":"Anneau","lvl":"Niveau : 31","statistics":[{"Vitalité":{"min":"21","max":"30"}},{"Fuite":{"min":"2","max":"3"}},{"Résistance Neutre":{"min":"2","max":"3"}},{"Résistance Terre":{"min":"2","max":"3"}},{"Sagesse":{"min":"6","max":"10"}}]},{"name":"AMULETTE DE RAPINE","type":"Amulette","lvl":"Niveau : 31","statistics":[{"Vitalité":{"min":"36","max":"40"}},{"Intelligence":{"min":"16","max":"20"}},{}]},{"name":"LA MOUTHMOU","type":"Ceinture","lvl":"Niveau : 31","statistics":[{"Vitalité":{"min":"41","max":"60"}},{"Invocations":{"min":"1","max":""}},{"Fuite":{"min":"2","max":"3"}}]},{"name":"ANNEAU SOLO","type":"Anneau","lvl":"Niveau : 31","statistics":[{"Force":{"min":"7","max":"10"}},{"Agilité":{"min":"7","max":"10"}},{"Coups Critiques":{"min":"3","max":""}}]},{"name":"SOUVENIR D'ENUTROF","type":"Anneau","lvl":"Niveau : 30","statistics":[{"Sagesse":{"min":"11","max":"15"}},{"Chance":{"min":"11","max":"15"}},{"Vitalité":{"min":"11","max":"15"}}]},{"name":"TOADY","type":"Chapeau","lvl":"Niveau : 30","statistics":[{"Agilité":{"min":"41","max":"50"}}]},{"name":"BOTTES DU BOIS DE L'EST","type":"Bottes","lvl":"Niveau : 30","statistics":[{"Force":{"min":"6","max":"10"}},{"Vitalité":{"min":"16","max":"25"}},{"Intelligence":{"min":"6","max":"10"}},{"Agilité":{"min":"6","max":"10"}},{"Chance":{"min":"6","max":"10"}},{}]},{"name":"POMPANNEAU","type":"Anneau","lvl":"Niveau : 30","statistics":[{"Sagesse":{"min":"11","max":"15"}},{"Intelligence":{"min":"11","max":"15"}},{}]},{"name":"ANNEAU DE L'ARAKNE CÉLESTE","type":"Anneau","lvl":"Niveau : 30","statistics":[]},{"name":"BOTTES DES GROCORICOS","type":"Bottes","lvl":"Niveau : 30","statistics":[{},{"Force":{"min":"16","max":"25"}},{"Chance":{"min":"16","max":"25"}},{"PO":{"min":"1","max":""}}]},{"name":"CEINTURE VERRÉHOR","type":"Ceinture","lvl":"Niveau : 30","statistics":[{},{"Force":{"min":"16","max":"20"}},{"Agilité":{"min":"16","max":"20"}},{"Sagesse":{"min":"11","max":"15"}}]},{"name":"CEINTURE FULGURANTE","type":"Ceinture","lvl":"Niveau : 30","statistics":[{"PA":{"min":"1","max":""}},{"Vitalité":{"min":"1","max":"30"}},{"Sagesse":{"min":"1","max":"30"}},{"Dommages":{"min":"1","max":"3"}}]},{"name":"PASSÉ DE XÉLOR","type":"Anneau","lvl":"Niveau : 30","statistics":[{"Sagesse":{"min":"11","max":"15"}},{"Intelligence":{"min":"11","max":"15"}},{"Vitalité":{"min":"11","max":"15"}}]},{"name":"SAC DU RÉCOLTEUR","type":"Sac à dos","lvl":"Niveau : 30","statistics":[{"Pods":{"min":"251","max":"400"}},{"Vitalité":{"min":"6","max":"10"}},{"Force":{"min":"6","max":"15"}},{}]},{"name":"BOB DU PAYSAN","type":"Chapeau","lvl":"Niveau : 30","statistics":[{"Sagesse":{"min":"6","max":"10"}},{"Retrait PM":{"min":"3","max":"4"}},{"Chance":{"min":"7","max":"10"}},{"Force":{"min":"7","max":"10"}},{"Vitalité":{"min":"16","max":"25"}}]},{"name":"CAPE DE LA FIN PATRAQUE","type":"Cape","lvl":"Niveau : 30","statistics":[{"Vitalité":{"min":"20","max":""}},{"Sagesse":{"min":"10","max":""}}]},{"name":"CEINTURE DE L'ARAKNE CÉLESTE","type":"Ceinture","lvl":"Niveau : 30","statistics":[]},{"name":"BOTTES DE L'ARAKNE CÉLESTE","type":"Bottes","lvl":"Niveau : 30","statistics":[{"Vitalité":{"min":"11","max":"20"}},{},{"PM":{"min":"1","max":""}}]},{"name":"AMULETTE DE L'ARAKNE CÉLESTE","type":"Amulette","lvl":"Niveau : 30","statistics":[]},{"name":"AMULETTE VERRÉHOR","type":"Amulette","lvl":"Niveau : 30","statistics":[{},{"Force":{"min":"16","max":"25"}},{"Agilité":{"min":"16","max":"25"}},{"PO":{"min":"1","max":""}}]},{"name":"HOUDE","type":"Chapeau","lvl":"Niveau : 30","statistics":[{"Chance":{"min":"31","max":"40"}},{"Coups Critiques":{"min":"1","max":"2"}}]},{"name":"CAPE DE BONNE ESPÉRANCE","type":"Cape","lvl":"Niveau : 30","statistics":[{"Chance":{"min":"21","max":"30"}},{"Dommages Eau":{"min":"2","max":""}},{"Vitalité":{"min":"7","max":"10"}},{"Dommages Terre":{"min":"-2","max":"-undefined"}},{"Coups Critiques":{"min":"-4","max":"-undefined"}},{"PO":{"min":"1","max":""}},{"Force":{"min":"-30","max":"-undefined"}}]},{"name":"CAPOUZE DES CHAMPS","type":"Cape","lvl":"Niveau : 30","statistics":[{"Vitalité":{"min":"21","max":"25"}},{"Initiative":{"min":"61","max":"100"}},{"Intelligence":{"min":"11","max":"15"}},{"Agilité":{"min":"11","max":"15"}},{"Sagesse":{"min":"4","max":"6"}}]},{"name":"AMULETTE DU MOSKITO","type":"Amulette","lvl":"Niveau : 30","statistics":[{"Chance":{"min":"16","max":"20"}},{"Vitalité":{"min":"16","max":"25"}},{"Sagesse":{"min":"6","max":"10"}},{"Dommages Eau":{"min":"2","max":"3"}},{"Retrait PM":{"min":"1","max":"2"}}]},{"name":"BOUCLIER DU BOUFTOU","type":"Bouclier","lvl":"Niveau : 30","statistics":[{"Vitalité":{"min":"20","max":""}},{"Initiative":{"min":"50","max":""}}]},{"name":"ANNEAU CRISTALINE","type":"Anneau","lvl":"Niveau : 30","statistics":[{"Sagesse":{"min":"11","max":"15"}},{"Chance":{"min":"11","max":"15"}},{}]},{"name":"MASQUE DE TAFF","type":"Chapeau","lvl":"Niveau : 30","statistics":[{"Puissance":{"min":"11","max":"15"}},{"Sagesse":{"min":"7","max":"10"}},{"Invocations":{"min":"1","max":""}},{"Fuite":{"min":"2","max":"3"}}]},{"name":"CHAPEAU DE L'AGENCE TOURISTE","type":"Chapeau","lvl":"Niveau : 30","statistics":[{"Vitalité":{"min":"51","max":"80"}},{"Dommages":{"min":"3","max":"5"}},{"Sagesse":{"min":"7","max":"10"}},{}]},{"name":"CAPE DU JUSTICIER","type":"Cape","lvl":"Niveau : 30","statistics":[{"Puissance":{"min":"21","max":"30"}},{"Vitalité":{"min":"31","max":"40"}},{"Soins":{"min":"3","max":"5"}},{}]},{"name":"CEINTURE DE PHONG HUSS","type":"Ceinture","lvl":"Niveau : 30","statistics":[{"Force":{"min":"21","max":"25"}},{"Dommages":{"min":"1","max":"2"}},{}]},{"name":"COIFFE DE L'ARAKNE CÉLESTE","type":"Chapeau","lvl":"Niveau : 30","statistics":[]},{"name":"LA BIBELAW","type":"Amulette","lvl":"Niveau : 30","statistics":[{"Vitalité":{"min":"16","max":"20"}},{"% Résistance Air":{"min":"2","max":"3"}},{"% Résistance Eau":{"min":"2","max":"3"}},{"% Résistance Feu":{"min":"2","max":"3"}},{"% Résistance Terre":{"min":"2","max":"3"}}]},{"name":"SANDALES MACIEN","type":"Bottes","lvl":"Niveau : 30","statistics":[{"Vitalité":{"min":"21","max":"25"}},{"Agilité":{"min":"21","max":"30"}},{"Coups Critiques":{"min":"2","max":""}},{"Tacle":{"min":"2","max":"3"}}]},{"name":"AILES EN BOIS AMÉLIORÉES","type":"Cape","lvl":"Niveau : 30","statistics":[{"Pods":{"min":"151","max":"200"}},{"Initiative":{"min":"151","max":"200"}}]},{"name":"CHAPEAU DE LA FIN PATRAQUE","type":"Chapeau","lvl":"Niveau : 30","statistics":[{"PO":{"min":"1","max":""}},{"Vitalité":{"min":"10","max":""}}]},{"name":"BOTTES EN PEAU DE PRESPIC","type":"Bottes","lvl":"Niveau : 30","statistics":[{"Vitalité":{"min":"1","max":"50"}},{"Sagesse":{"min":"1","max":"5"}},{"Initiative":{"min":"26","max":"50"}},{"Puissance":{"min":"1","max":"10"}},{}]},{"name":"CAPE DE L'ARAKNE CÉLESTE","type":"Cape","lvl":"Niveau : 30","statistics":[]},{"name":"CEINTURE DES GROCORICOS","type":"Ceinture","lvl":"Niveau : 30","statistics":[{},{"Force":{"min":"16","max":"20"}},{"Chance":{"min":"16","max":"20"}},{"Sagesse":{"min":"11","max":"15"}}]},{"name":"L'ECALISEUR","type":"Anneau","lvl":"Niveau : 29","statistics":[{"Chance":{"min":"11","max":"15"}},{"Vitalité":{"min":"16","max":"20"}},{"Dommages":{"min":"2","max":""}}]},{"name":"AMULETTE DE SHIKA","type":"Amulette","lvl":"Niveau : 29","statistics":[{"Vitalité":{"min":"41","max":"50"}},{"Sagesse":{"min":"7","max":"10"}},{"Initiative":{"min":"151","max":"160"}},{"Tacle":{"min":"2","max":"3"}}]},{"name":"CASQUE DE BOUFBOWL","type":"Chapeau","lvl":"Niveau : 29","statistics":[{"% Résistance Terre":{"min":"2","max":"3"}},{"% Résistance Neutre":{"min":"2","max":"3"}},{"Vitalité":{"min":"31","max":"40"}}]},{"name":"KABALE","type":"Amulette","lvl":"Niveau : 29","statistics":[{"Sagesse":{"min":"11","max":"15"}},{"Intelligence":{"min":"21","max":"30"}}]},{"name":"BOTTES CHAMPÊTRES","type":"Bottes","lvl":"Niveau : 29","statistics":[{"Vitalité":{"min":"21","max":"30"}},{"Intelligence":{"min":"11","max":"15"}},{"Agilité":{"min":"11","max":"15"}},{"Sagesse":{"min":"6","max":"10"}}]},{"name":"ANNEAU DU SANGLIER","type":"Anneau","lvl":"Niveau : 29","statistics":[{"Sagesse":{"min":"7","max":"10"}},{"Vitalité":{"min":"11","max":"15"}},{"Force":{"min":"11","max":"15"}},{"Dommages Poussée":{"min":"2","max":""}}]},{"name":"CEINTURE FLEURIE","type":"Ceinture","lvl":"Niveau : 29","statistics":[{"Initiative":{"min":"31","max":"50"}},{"Intelligence":{"min":"6","max":"10"}},{"Agilité":{"min":"6","max":"10"}},{"Résistance Eau":{"min":"3","max":"5"}},{"Sagesse":{"min":"5","max":"8"}},{"Dommages Feu":{"min":"1","max":"2"}},{"Dommages Air":{"min":"1","max":"2"}}]},{"name":"COIFFE CHAMPÊTRE","type":"Chapeau","lvl":"Niveau : 29","statistics":[{"Invocations":{"min":"1","max":""}},{"Fuite":{"min":"2","max":"3"}},{"Sagesse":{"min":"11","max":"15"}}]},{"name":"AMULETTE DES CHAMPS","type":"Amulette","lvl":"Niveau : 28","statistics":[{"Vitalité":{"min":"21","max":"30"}},{"Agilité":{"min":"11","max":"15"}},{"Fuite":{"min":"2","max":"3"}},{"Dommages Air":{"min":"2","max":"3"}},{"Résistance Terre":{"min":"3","max":"5"}}]},{"name":"BOTTES DE BOUFBOWL","type":"Bottes","lvl":"Niveau : 28","statistics":[{"Dommages":{"min":"2","max":""}},{"Puissance":{"min":"7","max":"10"}},{"Vitalité":{"min":"21","max":"30"}},{"Tacle":{"min":"2","max":"3"}},{"Fuite":{"min":"2","max":"3"}}]},{"name":"BANANA CAPE","type":"Cape","lvl":"Niveau : 28","statistics":[{"Puissance":{"min":"11","max":"15"}},{"Initiative":{"min":"101","max":"150"}},{"Vitalité":{"min":"41","max":"60"}}]},{"name":"LA BROCHE HÈTE","type":"Amulette","lvl":"Niveau : 28","statistics":[{"Sagesse":{"min":"16","max":"20"}},{"Initiative":{"min":"100","max":""}},{"Vitalité":{"min":"31","max":"40"}}]},{"name":"LA CROQUEUSE","type":"Ceinture","lvl":"Niveau : 28","statistics":[{"Intelligence":{"min":"31","max":"40"}},{"% Résistance Feu":{"min":"2","max":""}},{"% Résistance Neutre":{"min":"-2","max":"-undefined"}},{"Force":{"min":"-40","max":"-undefined"}},{"Soins":{"min":"7","max":"10"}},{"Vitalité":{"min":"21","max":"30"}},{"Force":{"min":"40","max":"80"}}]},{"name":"ANNEAU CHAMPÊTRE","type":"Anneau","lvl":"Niveau : 28","statistics":[{"Vitalité":{"min":"16","max":"25"}},{"Dommages Air":{"min":"2","max":"3"}},{"Dommages Feu":{"min":"2","max":"3"}},{"Sagesse":{"min":"3","max":"5"}}]},{"name":"SANGLATURE","type":"Ceinture","lvl":"Niveau : 27","statistics":[{"Vitalité":{"min":"16","max":"20"}},{"% Résistance Air":{"min":"2","max":"3"}},{"Dommages Poussée":{"min":"4","max":"6"}},{"% Résistance Feu":{"min":"1","max":"2"}}]},{"name":"PIEDS DU SANGLIER","type":"Bottes","lvl":"Niveau : 27","statistics":[{"Force":{"min":"11","max":"15"}},{"Vitalité":{"min":"16","max":"25"}},{"Sagesse":{"min":"7","max":"10"}},{"Dommages Poussée":{"min":"3","max":"5"}}]},{"name":"LA CÉLÉBRITÉ","type":"Amulette","lvl":"Niveau : 27","statistics":[{"PO":{"min":"1","max":""}},{"Vitalité":{"min":"4","max":""}}]},{"name":"CAPE DE L'AGENCE TOURISTE","type":"Cape","lvl":"Niveau : 27","statistics":[{"Vitalité":{"min":"40","max":"60"}},{"Initiative":{"min":"51","max":"70"}},{"Agilité":{"min":"7","max":"10"}},{"Sagesse":{"min":"10","max":"15"}},{}]},{"name":"CEINTURE D'ENDURANCE","type":"Ceinture","lvl":"Niveau : 27","statistics":[{"Force":{"min":"31","max":"40"}},{"Vitalité":{"min":"41","max":"60"}},{"Agilité":{"min":"-30","max":"-undefined"}}]},{"name":"CEINTURE DU BANDIT","type":"Ceinture","lvl":"Niveau : 27","statistics":[{"Coups Critiques":{"min":"2","max":"3"}},{"Dommages Air":{"min":"2","max":"3"}},{"% Résistance Air":{"min":"-2","max":"-undefined"}},{"% Résistance Feu":{"min":"-2","max":"-undefined"}},{"% Résistance Neutre":{"min":"-2","max":"-undefined"}},{"% Résistance Eau":{"min":"-2","max":"-undefined"}},{"% Résistance Terre":{"min":"-2","max":"-undefined"}},{"PO":{"min":"1","max":""}},{"Fuite":{"min":"1","max":"2"}},{"Agilité":{"min":"7","max":"10"}}]},{"name":"CEINTUREMUDA DU PAYSAN","type":"Ceinture","lvl":"Niveau : 27","statistics":[{"Vitalité":{"min":"16","max":"25"}},{"Chance":{"min":"7","max":"10"}},{"Force":{"min":"7","max":"10"}},{"Sagesse":{"min":"3","max":"5"}},{"Dommages Eau":{"min":"1","max":"2"}},{"Dommages Terre":{"min":"1","max":"2"}}]},{"name":"L'ECRABOUILLEUR DE IOP","type":"Bottes","lvl":"Niveau : 27","statistics":[{"Force":{"min":"21","max":"25"}},{"Intelligence":{"min":"-10","max":"-undefined"}},{"Agilité":{"min":"21","max":"25"}},{"Dommages Air":{"min":"2","max":""}},{"Dommages Feu":{"min":"2","max":""}}]},{"name":"CEINTURE DE CÉLÉRITÉ","type":"Ceinture","lvl":"Niveau : 27","statistics":[{"Agilité":{"min":"21","max":"30"}},{"Sagesse":{"min":"-6","max":"--15"}},{"% Résistance Air":{"min":"2","max":"3"}},{"Fuite":{"min":"4","max":"5"}}]},{"name":"POMPAMULETTE","type":"Amulette","lvl":"Niveau : 27","statistics":[{"PO":{"min":"1","max":""}},{"Vitalité":{"min":"4","max":""}},{}]},{"name":"JOUIK KRAMPE","type":"Chapeau","lvl":"Niveau : 26","statistics":[{"Invocations":{"min":"1","max":""}},{"Intelligence":{"min":"31","max":"40"}},{"Agilité":{"min":"30","max":""}},{}]},{"name":"FÉCALISEUR DU GUERRIER","type":"Anneau","lvl":"Niveau : 26","statistics":[{"% Résistance Terre":{"min":"2","max":""}},{"% Résistance Neutre":{"min":"2","max":""}},{"Vitalité":{"min":"16","max":"20"}}]},{"name":"CEINTURE PIQUANTE","type":"Ceinture","lvl":"Niveau : 26","statistics":[{"Sagesse":{"min":"11","max":"15"}},{"Fuite":{"min":"4","max":"5"}},{"Coups Critiques":{"min":"2","max":"3"}}]},{"name":"ENTENTE","type":"Amulette","lvl":"Niveau : 26","statistics":[{"Force":{"min":"7","max":"10"}},{"Agilité":{"min":"7","max":"10"}},{"Sagesse":{"min":"2","max":"3"}},{"Intelligence":{"min":"7","max":"10"}},{"Chance":{"min":"7","max":"10"}}]},{"name":"FÉCALISEUR DU MAGICIEN","type":"Anneau","lvl":"Niveau : 26","statistics":[{"% Résistance Eau":{"min":"2","max":""}},{"% Résistance Air":{"min":"2","max":""}},{"% Résistance Feu":{"min":"2","max":""}}]},{"name":"ANNEAU DU PIOU VIOLET","type":"Anneau","lvl":"Niveau : 26","statistics":[{"Vitalité":{"min":"7","max":"10"}},{"Puissance":{"min":"6","max":"10"}},{"Dommages":{"min":"1","max":"2"}}]},{"name":"ALLIANCE DE SILIMELLE","type":"Anneau","lvl":"Niveau : 26","statistics":[{"Sagesse":{"min":"21","max":"25"}},{"Dommages Air":{"min":"-2","max":"-undefined"}},{"Dommages Eau":{"min":"-2","max":"-undefined"}},{"Dommages Feu":{"min":"-2","max":"-undefined"}},{"Dommages Terre":{"min":"-2","max":"-undefined"}},{"Retrait PA":{"min":"2","max":""}},{"Retrait PM":{"min":"2","max":""}}]},{"name":"BONNET DU GLUTIN","type":"Chapeau","lvl":"Niveau : 25","statistics":[{"Vitalité":{"min":"31","max":"40"}},{"Fuite":{"min":"3","max":"4"}},{"Chance":{"min":"7","max":"10"}},{"Agilité":{"min":"7","max":"10"}}]},{"name":"ANNEAU DU SANGLIER CÉLESTE","type":"Anneau","lvl":"Niveau : 25","statistics":[]},{"name":"ANNEAU MÈR","type":"Anneau","lvl":"Niveau : 25","statistics":[{"Tacle":{"min":"2","max":"3"}},{"Vitalité":{"min":"41","max":"60"}},{"Chance":{"min":"100","max":"100"}}]},{"name":"AMULETTE DU BANDIT","type":"Amulette","lvl":"Niveau : 25","statistics":[{"Vitalité":{"min":"11","max":"15"}},{"Dommages Air":{"min":"1","max":"2"}},{"Coups Critiques":{"min":"2","max":"3"}},{"Agilité":{"min":"16","max":"20"}},{"Initiative":{"min":"61","max":"100"}}]},{"name":"COIFFE DU SANGLIER CÉLESTE","type":"Chapeau","lvl":"Niveau : 25","statistics":[]},{"name":"SAC DU PETIT RÉCOLTEUR","type":"Sac à dos","lvl":"Niveau : 25","statistics":[{"Pods":{"min":"151","max":"250"}},{}]},{"name":"CAPE DE L'HOMME OURS","type":"Cape","lvl":"Niveau : 25","statistics":[{"Vitalité":{"min":"16","max":"20"}},{"Agilité":{"min":"6","max":"10"}},{"Intelligence":{"min":"6","max":"10"}},{"Dommages Feu":{"min":"2","max":"3"}},{"Dommages Air":{"min":"2","max":"3"}}]},{"name":"ANNEAU THÉ","type":"Anneau","lvl":"Niveau : 25","statistics":[{"Vitalité":{"min":"26","max":"35"}},{"Puissance":{"min":"11","max":"15"}},{"Sagesse":{"min":"3","max":"5"}}]},{"name":"MANTEAU DU GLUTIN","type":"Cape","lvl":"Niveau : 25","statistics":[{"Vitalité":{"min":"21","max":"30"}},{"Puissance":{"min":"11","max":"15"}},{"Fuite":{"min":"2","max":"3"}},{"Dommages":{"min":"2","max":""}}]},{"name":"CAPE DU SANGLIER CÉLESTE","type":"Cape","lvl":"Niveau : 25","statistics":[]},{"name":"AMULETTE DU SANGLIER CÉLESTE","type":"Amulette","lvl":"Niveau : 25","statistics":[]},{"name":"SAC RIPANT","type":"Sac à dos","lvl":"Niveau : 25","statistics":[{"Pods":{"min":"201","max":"250"}}]}]